soap_as_rest_server/__init__.py
soap_as_rest_server/__main__.py
soap_as_rest_server/app.py
soap_as_rest_server/config.py
soap_as_rest_server/elapsed.py
soap_as_rest_server/infos.py
soap_as_rest_server/json_converter.py
soap_as_rest_server/logger.py
soap_as_rest_server/main_handler.py
soap_as_rest_server/settings.py
soap_as_rest_server/soap_client.py
soap_as_rest_server/starter.py
soap_as_rest_server/template_helper.py
soap_as_rest_server/xml_converter.py
soap_as_rest_server-0.0.1.dist-info/LICENSE
soap_as_rest_server-0.0.1.dist-info/METADATA
soap_as_rest_server-0.0.1.dist-info/WHEEL
soap_as_rest_server-0.0.1.dist-info/top_level.txt
soap_as_rest_server-0.0.1.dist-info/RECORD
