Metadata-Version: 2.1
Name: soap-as-rest-server
Version: 0.0.1
Summary: Soap Proxy Module to get data from SOAP Services
Home-page: https://github.com/frankmendonca/soap-as-rest-server
Author: Frank Mendonca
Author-email: frankmed57@gmail.com
License: MIT
Keywords: soap,xml,json,rest
Platform: any
Classifier: Intended Audience :: Developers
Classifier: License :: OSI Approved :: MIT License
Classifier: Operating System :: OS Independent
Classifier: Programming Language :: Python
Classifier: Programming Language :: Python :: 3
Classifier: Topic :: Software Development :: Libraries
Requires-Python: >=3.6
Requires-Dist: tornado (==5.1.1)
Requires-Dist: requests (==2.22.0)
Requires-Dist: PyYAML (==5.1.2)
Requires-Dist: lxml (==4.4.1)
